{
    "Players": [
        {
            "Discord_Name":"Ice#5958",
            "Battle_Net":"ice#23440"
        },
        {
            "Discord_Name":"Galahad#7960",
            "Battle_Net":"back2front#2554"
        },
        {
            "Discord_Name":"Cookie#2074",
            "Battle_Net":"xSoulless#11777"
        },
        {
            "Discord_Name":"sushi#7916",
            "Battle_Net":"TorbsHubbie#1222"
        },
        {
            "Discord_Name":"DaiShan#4059",
            "Battle_Net":"DaiShan#1244"
        },
        {
            "Discord_Name":"Zenb0tta#0001",
            "Battle_Net":"Zenbotta#1162"
        },
        {
            "Discord_Name":"KrabKing#1159",
            "Battle_Net":"KingKrab#11976"
        },
        {
            "Discord_Name":"ehitburns#0342",
            "Battle_Net":"ehitburns#1180"
        },
        {
            "Discord_Name":"Wholesome#9164",
            "Battle_Net":"Wholesome#11342"
        },
        {
            "Discord_Name":"Kavat#6811",
            "Battle_Net":"Kavat#11424"
        },
        {
            "Discord_Name":"BallistikGamer2000#3008",
            "Battle_Net":"Ballistik#11170"
        },
        {
            "Discord_Name":"Willrocks147#7523",
            "Battle_Net":"Maximus#1525"
        },
        {
            "Discord_Name":"LandminePie#2412",
            "Battle_Net":"Synaptic#11263"
        },
        {
            "Discord_Name":"NonaiX#2976",
            "Battle_Net":"NonaiX#1184"
        },
        {
            "Discord_Name":"Manet#0518",
            "Battle_Net":"DreamWeaver#1486"
        },
        {
            "Discord_Name":"Caftstone#7516",
            "Battle_Net":"Caftstone#2218"
        },
        {
            "Discord_Name":"archer#1887",
            "Battle_Net":"GoodVibes#11523"
        },
        {
            "Discord_Name":"Roland of Billead#3295",
            "Battle_Net":"BillofLefts#1655"
        },
        {
            "Discord_Name":"DrKillinger#9754",
            "Battle_Net":"DrKillinger#11125"
        },
        {
            "Discord_Name":"McMurk#6235",
            "Battle_Net":"McMurk#1825"
        },
        {
            "Discord_Name":"Pandr#4913",
            "Battle_Net":"Pandr#11132"
        },
        {
            "Discord_Name":"Miska#8317",
            "Battle_Net":"MIŜKA#2437"
        },
        {
            "Discord_Name":"RealNegusBleed#4284",
            "Battle_Net":"YeezySama#1795"
        },
        {
            "Discord_Name":"CyberNinja",
            "Battle_Net":"CyberNinja#1393"
        },
        {
            "Discord_Name":"Halo2k 冷心#7163",
            "Battle_Net":"Ebisu#11785"
        },
        {
            "Discord_Name":"MamaMercy#8990",
            "Battle_Net":"MamaMercy#1364"
        },
        {
            "Discord_Name":"Pathos#3005",
            "Battle_Net":"Päthos#1121"
        },
        {
            "Discord_Name":"AdjustedSubz#3679",
            "Battle_Net":"AdjustedSubz#1888"
        },
        {
            "Discord_Name":"CZAR#8433",
            "Battle_Net":"CZAR#11840"
        },
        {
            "Discord_Name":"TaylorSwift#5815",
            "Battle_Net":"Tayl0rSwift#11290"
        },
        {
            "Discord_Name":"Glay#0001",
            "Battle_Net":"Deceit#11750"
        },
        {
            "Discord_Name":"Godzo#0001",
            "Battle_Net":"ŦØXIÇĐPŚ#1835"
        },
        {
            "Discord_Name":"ekhoowo#2695",
            "Battle_Net":"EKHOYEET#1417"
        },
        {
            "Discord_Name":"ariana#4861",
            "Battle_Net":"Naiara#11899"
        },
        {
            "Discord_Name":"Salty (ماثيو)#7848",
            "Battle_Net":"TampyWampy#1751"
        },
        {
            "Discord_Name":"Lime#5682",
            "Battle_Net":"Lime#12762"
        },
        {
            "Discord_Name":"24adrew#7683",
            "Battle_Net":"Adrew24#1500"
        },
        {
            "Discord_Name":"Elardoven#9554",
            "Battle_Net":"Doven#11631"
        },
        {
            "Discord_Name":"Cab00se#8405",
            "Battle_Net":"Cab00se#11434"
        },
        {
            "Discord_Name":"Krumpet#3700",
            "Battle_Net":"Krumpet#11144"
        },
        {
            "Discord_Name":"ninevolt#2705",
            "Battle_Net":"ninevolt#11463"
        },
        {
            "Discord_Name":"PreciousBearHoldingTangents#7464",
            "Battle_Net":"PreciousRoy#11619"
        },
        {
            "Discord_Name":"Ugopewpew#9800",
            "Battle_Net":"Morepewpew#11395"
        },
        {
            "Discord_Name":"Gambetto#1413",
            "Battle_Net":"Gambetto#11603"
        }
    ]
}